LICENSE
MANIFEST.in
README.md
setup.py
fastspt/__init__.py
fastspt/fastSPT_plot.py
fastspt/fastSPT_tools.py
fastspt/fastspt.py
fastspt/format4DN.py
fastspt/readers.py
fastspt/version.py
fastspt/writers.py
fastspt.egg-info/PKG-INFO
fastspt.egg-info/SOURCES.txt
fastspt.egg-info/dependency_links.txt
fastspt.egg-info/requires.txt
fastspt.egg-info/top_level.txt