Metadata-Version: 1.1
Name: fastspt
Version: 15.10
Summary: A library to perform kinetic modeling of fast single particle tracking experiments
Home-page: https://gitlab.com/tjian-darzacq-lab/Spot-On-cli
Author: Maxime Woringer, Anders Sejr Hansen
Author-email: maxime@woringer.fr
License: GPLv3+
Keywords: single particle tracking SPT kinetic modelling
Platform: UNKNOWN
Classifier: Development Status :: 5 - Production/Stable
Classifier: Intended Audience :: Science/Research
Classifier: Programming Language :: Python :: 2
Classifier: Programming Language :: Python :: 2.7
